ai4sqlite3/__init__.py
ai4sqlite3/__main__.py
ai4sqlite3/_version.py
ai4sqlite3-0.1.0.dist-info/LICENSE
ai4sqlite3-0.1.0.dist-info/METADATA
ai4sqlite3-0.1.0.dist-info/WHEEL
ai4sqlite3-0.1.0.dist-info/entry_points.txt
ai4sqlite3-0.1.0.dist-info/top_level.txt
ai4sqlite3-0.1.0.dist-info/RECORD
