Metadata-Version: 2.1
Name: ai4sqlite3
Version: 0.1.0
Summary: LLM query assistant for SQLite3 databases
Project-URL: repository, https://github.com/mlin/ai4sqlite3.git
Classifier: License :: OSI Approved :: MIT License
Requires-Python: ~=3.8
License-File: LICENSE
Requires-Dist: openai
Requires-Dist: alive-progress
Requires-Dist: getch
Requires-Dist: prettytable
Requires-Dist: prompt-toolkit
Provides-Extra: dev
Requires-Dist: setuptools ; extra == 'dev'
Requires-Dist: build ; extra == 'dev'
Requires-Dist: twine ; extra == 'dev'
Requires-Dist: pre-commit ; extra == 'dev'
Requires-Dist: black ; extra == 'dev'
Requires-Dist: ruff ; extra == 'dev'
